ct/__init__.py
ct/ct_loss.py
ct/functional/__init__.py
ct/functional/ct_loss.py
ct_loss-0.0.3.dist-info/LICENSE
ct_loss-0.0.3.dist-info/METADATA
ct_loss-0.0.3.dist-info/WHEEL
ct_loss-0.0.3.dist-info/top_level.txt
ct_loss-0.0.3.dist-info/RECORD
