Metadata-Version: 2.1
Name: ct-loss
Version: 0.0.3
Summary: The contrastive token loss for reducing generative repetition of augoregressive neural language models.
Home-page: https://github.com/ShaojieJiang/CT-Loss
Author: Shaojie Jiang
Author-email: shaojiejiang.1991@gmail.com
License: UNKNOWN
Project-URL: Bug Tracker, https://github.com/ShaojieJiang/CT-Loss/issues
Platform: UNKNOWN
Classifier: Programming Language :: Python :: 3
Classifier: License :: OSI Approved :: MIT License
Classifier: Operating System :: OS Independent
Requires-Python: >=3.7
License-File: LICENSE
Requires-Dist: torch (>=1.10.0)
